{"id":"mw-business","title":"MW 葡萄酒商業","description":"Master of Wine 葡萄酒產業、市場、當代議題","duration":"40分鐘","free":false,"chapters":[{"id":1,"title":"全球葡萄酒市場","duration":"7分鐘","content":"產量、消費、進出口。主要生產國與消費國。市場趨勢與變化。","quiz":[{"question":"葡萄酒最大生產國？","options":["美國","義大利、法國、西班牙","澳洲","智利"],"correctIndex":1}]},{"id":2,"title":"供應鏈與通路","duration":"7分鐘","content":"生產者到消費者路徑。進口商、經銷商、零售。電商、DTC。各國法規差異。","quiz":[{"question":"DTC 優勢？","options":["僅通路","生產者直達消費者","僅零售","無"],"correctIndex":1}]},{"id":3,"title":"定價與品牌","duration":"6分鐘","content":"成本結構、利潤率。品牌定位、溢價。評分、獎項影響。","quiz":[{"question":"高分評分常見影響？","options":["無","需求與價格上升","僅品質","無"],"correctIndex":1}]},{"id":4,"title":"永續與社會責任","duration":"6分鐘","content":"有機、永續認證。包裝、碳足跡。勞工、社區。","quiz":[{"question":"輕量瓶目的？","options":["僅美觀","降低碳足跡","增重","無"],"correctIndex":1}]},{"id":5,"title":"當代議題","duration":"5分鐘","content":"氣候變遷、疫情、貿易戰。消費趨勢：低酒精、有機、自然酒。未來展望。","quiz":[{"question":"低酒精趨勢反映？","options":["無","健康意識、法規","僅口味","無"],"correctIndex":1}]}]}
